longhorn/__init__.py
longhorn/actions.py
longhorn/blueprint.py
longhorn/config.py
longhorn/database.py
longhorn/format/__init__.py
longhorn/format/article.py
longhorn/format/for_web.py
longhorn/format/formatter.py
longhorn/format/mastodon_quoter.py
longhorn/format/test_article.py
longhorn/format/test_for_web.py
longhorn/format/test_formatter.py
longhorn/format/test_mastodon_quoter.py
longhorn/models.py
longhorn/post.py
longhorn/setup.py
longhorn/store.py
longhorn/templates/comment.html
longhorn/templates/index.html
longhorn/templates/info.html
longhorn/templates/page.html
longhorn/test_actions.py
longhorn/test_blueprint.py
longhorn/test_config.py
longhorn/test_store.py
longhorn-0.1.0.dist-info/METADATA
longhorn-0.1.0.dist-info/WHEEL
longhorn-0.1.0.dist-info/RECORD
