Metadata-Version: 2.1
Name: longhorn
Version: 0.1.0
Summary: Blog that publishes both to web, atom, and ActivityPub (as a Client)
Home-page: https://codeberg.org/bovine/longhorn
License: MIT
Author: Helge
Author-email: helge.krueger@gmail.com
Requires-Python: >=3.10,<4.0
Classifier: License :: OSI Approved :: MIT License
Classifier: Programming Language :: Python :: 3
Classifier: Programming Language :: Python :: 3.10
Classifier: Programming Language :: Python :: 3.11
Requires-Dist: aerich (>=0.7.1,<0.8.0)
Requires-Dist: aiohttp (>=3.8.4,<4.0.0)
Requires-Dist: beautifulsoup4 (>=4.11.2,<5.0.0)
Requires-Dist: black (>=23.1.0,<24.0.0)
Requires-Dist: bleach (>=6.0.0,<7.0.0)
Requires-Dist: bovine (>=0.2.0,<0.3.0)
Requires-Dist: feedwerk (>=1.1.0,<2.0.0)
Requires-Dist: markdown (>=3.4.1,<4.0.0)
Requires-Dist: pygments (>=2.14.0,<3.0.0)
Requires-Dist: quart (>=0.18.3,<0.19.0)
Requires-Dist: tortoise-orm (>=0.19.3,<0.20.0)
Project-URL: Documentation, https://longhorn.readthedocs.io/en/latest/
Project-URL: Repository, https://codeberg.org/bovine/longhorn
